pypowsybl2grid/__init__.py
pypowsybl2grid/pypowsybl_backend.py
pypowsybl2grid/util.py
pypowsybl2grid-0.3.0.dist-info/LICENSE
pypowsybl2grid-0.3.0.dist-info/METADATA
pypowsybl2grid-0.3.0.dist-info/WHEEL
pypowsybl2grid-0.3.0.dist-info/RECORD
