Metadata-Version: 2.1
Name: pypowsybl2grid
Version: 0.3.0
Summary: An integration between Grid2op and PyPowSybl
License: MPL-2.0
Author: Geoffroy Jamgotchian
Author-email: geoffroy.jamgotchian@rte-france.com
Requires-Python: >=3.9,<4.0
Classifier: License :: OSI Approved
Classifier: Programming Language :: Python :: 3
Classifier: Programming Language :: Python :: 3.9
Classifier: Programming Language :: Python :: 3.10
Classifier: Programming Language :: Python :: 3.11
Classifier: Programming Language :: Python :: 3.12
Classifier: Programming Language :: Python :: 3.13
Requires-Dist: grid2op (>=1.10.5,<2.0.0)
Requires-Dist: numpy (==1.26.4)
Requires-Dist: pypowsybl (>=1.11.0,<2.0.0)
Requires-Dist: sortedcontainers (>=2.4.0,<3.0.0)
